terminaluse/.fern/metadata.json
terminaluse/.fernignore
terminaluse/__init__.py
terminaluse/_client.py
terminaluse/agent_api_keys/__init__.py
terminaluse/agent_api_keys/client.py
terminaluse/agent_api_keys/raw_client.py
terminaluse/agents/__init__.py
terminaluse/agents/branches/__init__.py
terminaluse/agents/branches/client.py
terminaluse/agents/branches/raw_client.py
terminaluse/agents/client.py
terminaluse/agents/environments/__init__.py
terminaluse/agents/environments/branches/__init__.py
terminaluse/agents/environments/branches/client.py
terminaluse/agents/environments/branches/raw_client.py
terminaluse/agents/environments/client.py
terminaluse/agents/environments/raw_client.py
terminaluse/agents/environments/secrets/__init__.py
terminaluse/agents/environments/secrets/client.py
terminaluse/agents/environments/secrets/raw_client.py
terminaluse/agents/raw_client.py
terminaluse/agents/secrets/__init__.py
terminaluse/agents/secrets/client.py
terminaluse/agents/secrets/raw_client.py
terminaluse/agents/versions/__init__.py
terminaluse/agents/versions/client.py
terminaluse/agents/versions/raw_client.py
terminaluse/api_keys/__init__.py
terminaluse/api_keys/client.py
terminaluse/api_keys/raw_client.py
terminaluse/authentication/__init__.py
terminaluse/authentication/client.py
terminaluse/authentication/raw_client.py
terminaluse/authorization_internal/__init__.py
terminaluse/authorization_internal/client.py
terminaluse/authorization_internal/raw_client.py
terminaluse/branches/__init__.py
terminaluse/branches/client.py
terminaluse/branches/events/__init__.py
terminaluse/branches/events/client.py
terminaluse/branches/events/raw_client.py
terminaluse/branches/raw_client.py
terminaluse/branches/versions/__init__.py
terminaluse/branches/versions/client.py
terminaluse/branches/versions/raw_client.py
terminaluse/cli_authentication/__init__.py
terminaluse/cli_authentication/client.py
terminaluse/cli_authentication/raw_client.py
terminaluse/client.py
terminaluse/core/__init__.py
terminaluse-0.20.1.dist-info/METADATA
terminaluse-0.20.1.dist-info/WHEEL
terminaluse-0.20.1.dist-info/entry_points.txt
terminaluse-0.20.1.dist-info/RECORD
