Metadata-Version: 2.4
Name: terminaluse
Version: 0.20.1
Summary: 
Requires-Python: >=3.12
Classifier: Intended Audience :: Developers
Classifier: Operating System :: MacOS
Classifier: Operating System :: Microsoft :: Windows
Classifier: Operating System :: OS Independent
Classifier: Operating System :: POSIX
Classifier: Operating System :: POSIX :: Linux
Classifier: Programming Language :: Python
Classifier: Programming Language :: Python :: 3
Classifier: Programming Language :: Python :: 3.12
Classifier: Programming Language :: Python :: 3.13
Classifier: Programming Language :: Python :: 3.14
Classifier: Programming Language :: Python :: 3.10
Classifier: Programming Language :: Python :: 3.11
Classifier: Programming Language :: Python :: 3.8
Classifier: Programming Language :: Python :: 3.9
Classifier: Topic :: Software Development :: Libraries :: Python Modules
Classifier: Typing :: Typed
Requires-Dist: aiohttp (>=3.10.10,<4.0.0)
Requires-Dist: claude-agent-sdk (>=0.1.17,<0.2.0)
Requires-Dist: fastapi (>=0.115.0,<0.116.0)
Requires-Dist: httpx (>=0.21.2)
Requires-Dist: jinja2 (>=3.1.3,<4.0.0)
Requires-Dist: jsonref (>=1.1.0,<2.0.0)
Requires-Dist: jsonschema (>=4.23.0,<5.0.0)
Requires-Dist: opentelemetry-api (>=1.20.0)
Requires-Dist: opentelemetry-instrumentation-fastapi (>=0.44b0)
Requires-Dist: opentelemetry-instrumentation-httpx (>=0.44b0)
Requires-Dist: opentelemetry-sdk (>=1.20.0)
Requires-Dist: pydantic (>=1.9.2)
Requires-Dist: pydantic-core (>=2.18.2)
Requires-Dist: python-on-whales (>=0.73.0,<0.74.0)
Requires-Dist: python-ulid (>=3.0.0,<4.0.0)
Requires-Dist: pyyaml (>=6.0.2,<7.0.0)
Requires-Dist: pyzstd (>=0.16.0,<0.17.0)
Requires-Dist: questionary (>=2.0.1,<3.0.0)
Requires-Dist: rich (>=13.9.2,<14.0.0)
Requires-Dist: temporalio (>=1.18.2,<2.0.0)
Requires-Dist: tenacity (>=8.0.0,<9.0.0)
Requires-Dist: typer (>=0.16,<0.17)
Requires-Dist: typing_extensions (>=4.0.0)
Requires-Dist: uvicorn (>=0.31.1,<0.32.0)
Requires-Dist: yaspin (>=3.1.0,<4.0.0)
Project-URL: Repository, https://github.com/terminal-use/monorepo
